mongodf/__init__.py
mongodf/cache.py
mongodf/column.py
mongodf/dataframe.py
mongodf/exception.py
mongodf/filter.py
mongodf/utils.py
mongodf-0.1.16.dist-info/METADATA
mongodf-0.1.16.dist-info/WHEEL
mongodf-0.1.16.dist-info/top_level.txt
mongodf-0.1.16.dist-info/RECORD
