Metadata-Version: 2.4
Name: mongodf
Version: 0.1.16
Home-page: https://github.com/VK/mongodf
License: MIT
Keywords: mongoDB pandas dataframe filter
Requires-Dist: pymongo
Requires-Dist: pandas
Dynamic: description
Dynamic: description-content-type
Dynamic: home-page
Dynamic: keywords
Dynamic: license
Dynamic: requires-dist
